etranslate/__init__.py
etranslate/translate.py
etranslate-0.1.0.dist-info/LICENSE
etranslate-0.1.0.dist-info/METADATA
etranslate-0.1.0.dist-info/WHEEL
etranslate-0.1.0.dist-info/top_level.txt
etranslate-0.1.0.dist-info/RECORD
