Metadata-Version: 2.1
Name: etranslate
Version: 0.1.0
Summary: etranslate is a free and unlimited python library for translate your texts
Home-page: https://github.com/ixabolfazl/etranslate
Author: Abolfazl Khalili
Author-email: kabolfazl39@gmail.com.org
License: MIT
Keywords: translate
Classifier: Development Status :: 5 - Production/Stable
Classifier: Intended Audience :: Education
Classifier: Operating System :: Microsoft :: Windows :: Windows 10
Classifier: License :: OSI Approved :: MIT License
Classifier: Programming Language :: Python :: 3
Requires-Python: >=3.7
License-File: LICENSE
Requires-Dist: requests
